{
  "Author": "Aki, k-kz, ele-starshade, damolitionn, Taurenkey, Augporto, grimgal",
  "Name": "XIVSlothCombo",
  "InternalName": "XIVSlothCombo",
  "AssemblyVersion": "3.0.12.0",
  "Description": "Condenses combos and mutually exclusive abilities onto a single button - and then some.",
  "ApplicableVersion": "any",
  "RepoUrl": "https://github.com/Nik-Potokar/XIVSlothCombo",
  "DalamudApiLevel": 6,
  "LoadPriority": 0,
  "ImageUrls": [
    "https://i.imgur.com/UeRukF8.png"
  ],
  "IconUrl": "https://i.imgur.com/UeRukF8.png",
  "Punchline": "Condenses combos and mutually exclusive abilities onto a single button - and then some.",
  "Changelog": "Samurai Rework is here! Along with Features, Fixes & Enhancements for PvP-Globals, AST, DRK, GNB, NIN, PLD, RDM, SAM, SMN, WAR and WHM. Please check the project's GitHub or Discord for a full changelog."
}